Workbook

Sheet Base
A1: Subscriber ID | B1: Name | C1: Plan | D1: Start Date | E1: Auto Renewal | F1: Subscription Price | G1: Subscription Type | H1: EA Play Season Pass | I1: EA Play Season Pass Price | J1: Minecraft Season Pass | K1: Minecraft Season Pass Price | L1: Coupon Value | M1: Total Value
A2: SUB-0001 | B2: Subscriber 001 | C2: Ultimate | D2: 45292 | E2: No | F2: 30 | G2: Monthly | H2: Yes | I2: 10 | J2: No | K2: 0 | L2: 0 | M2: 40
A3: SUB-0002 | B3: Subscriber 002 | C3: Ultimate | D3: 45299 | E3: No | F3: 30 | G3: Quarterly | H3: Yes | I3: 10 | J3: No | K3: 0 | L3: 0 | M3: 40
A4: SUB-0003 | B4: Subscriber 003 | C4: Standard | D4: 45306 | E4: Yes | F4: 25 | G4: Annual | H4: Yes | I4: 10 | J4: Yes | K4: 20 | L4: 45 | M4: 10
A5: SUB-0004 | B5: Subscriber 004 | C5: Core | D5: 45313 | E5: Yes | F5: 30 | G5: Annual | H5: Yes | I5: 10 | J5: No | K5: 0 | L5: 0 | M5: 40
A6: SUB-0005 | B6: Subscriber 005 | C6: Standard | D6: 45320 | E6: No | F6: 35 | G6: Monthly | H6: Yes | I6: 10 | J6: Yes | K6: 20 | L6: 55 | M6: 10
A7: SUB-0006 | B7: Subscriber 006 | C7: Ultimate | D7: 45327 | E7: No | F7: 15 | G7: Annual | H7: Yes | I7: 10 | J7: Yes | K7: 20 | L7: 5 | M7: 40
A8: SUB-0007 | B8: Subscriber 007 | C8: Ultimate | D8: 45334 | E8: No | F8: 20 | G8: Quarterly | H8: Yes | I8: 10 | J8: Yes | K8: 20 | L8: 10 | M8: 40
A9: SUB-0008 | B9: Subscriber 008 | C9: Ultimate | D9: 45341 | E9: Yes | F9: 25 | G9: Monthly | H9: Yes | I9: 10 | J9: Yes | K9: 20 | L9: 15 | M9: 40
A10: SUB-0009 | B10: Subscriber 009 | C10: Core | D10: 45348 | E10: No | F10: 30 | G10: Quarterly | H10: Yes | I10: 10 | J10: Yes | K10: 20 | L10: 20 | M10: 40
A11: SUB-0010 | B11: Subscriber 010 | C11: Ultimate | D11: 45355 | E11: Yes | F11: 35 | G11: Annual | H11: Yes | I11: 10 | J11: Yes | K11: 20 | L11: 55 | M11: 10
A12: SUB-0011 | B12: Subscriber 011 | C12: Core | D12: 45362 | E12: Yes | F12: 15 | G12: Monthly | H12: Yes | I12: 10 | J12: Yes | K12: 20 | L12: 35 | M12: 10
A13: SUB-0012 | B13: Subscriber 012 | C13: Core | D13: 45369 | E13: No | F13: 20 | G13: Annual | H13: Yes | I13: 10 | J13: Yes | K13: 20 | L13: 10 | M13: 40
... A296: SUB-0295 | B296: Subscriber 295 | C296: Standard | D296: 45595 | E296: Yes | F296: 35 | G296: Annual | H296: Yes | I296: 10 | J296: Yes | K296: 20 | L296: 55 | M296: 10

Sheet Calculos
A1: Cálculos e indicadores
A3: Indicador | B3: Valor | D3: Plano | E3: Receita | G3: Periodicidade | H3: Receita
A4: Total de assinantes | B4: 295 | D4: Core | E4: =SUMIF(Base!$C$2:$C$296,D4,Base!$M$2:$M$296) -> 2757 | G4: Annual | H4: =SUMIF(Base!$G$2:$G$296,G4,Base!$M$2:$M$296) -> 2616
A5: Receita total | B5: 7633 | D5: Standard | E5: =SUMIF(Base!$C$2:$C$296,D5,Base!$M$2:$M$296) -> 2456 | G5: Monthly | H5: =SUMIF(Base!$G$2:$G$296,G5,Base!$M$2:$M$296) -> 2507
A6: EA Play Season Pass | B6: 2940 | D6: Ultimate | E6: =SUMIF(Base!$C$2:$C$296,D6,Base!$M$2:$M$296) -> 2420 | G6: Quarterly | H6: =SUMIF(Base!$G$2:$G$296,G6,Base!$M$2:$M$296) -> 2510
A7: Minecraft Season Pass | B7: 3880 | D7: Total | E7: =SUM(E4:E6) -> 7633 | G7: Total | H7: =SUM(H4:H6) -> 7633
A8: Renovação automática - Yes | B8: 3786
A9: Renovação automática - No | B9: 3847
D10: Auto Renewal | E10: Receita | G10: Add-on | H10: Receita
D11: Yes | E11: 3786 | G11: EA Play | H11: 2940
D12: No | E12: 3847 | G12: Minecraft | H12: 3880
D13: Total | E13: 7633 | G13: Total Add-ons | H13: 6820
D16: Plano | E16: Assinantes | G16: Mês | H16: Receita
D17: Core | E17: =COUNTIF(Base!$C$2:$C$296,D17) -> 99 | G17: 1 | H17: =SUMIFS(Base!$M$2:$M$296,Base!$D$2:$D$296,">="&DATE(2024,1,1),Base!$D$2:$D$296,"<"&DATE(2024,2,1)) -> 590
D18: Standard | E18: =COUNTIF(Base!$C$2:$C$296,D18) -> 98 | G18: 2 | H18: =SUMIFS(Base!$M$2:$M$296,Base!$D$2:$D$296,">="&DATE(2024,2,1),Base!$D$2:$D$296,"<"&DATE(2024,3,1)) -> 820
D19: Ultimate | E19: =COUNTIF(Base!$C$2:$C$296,D19) -> 98 | G19: 3 | H19: =SUMIFS(Base!$M$2:$M$296,Base!$D$2:$D$296,">="&DATE(2024,3,1),Base!$D$2:$D$296,"<"&DATE(2024,4,1)) -> 720
D20: Total | E20: 295 | G20: 4 | H20: =SUMIFS(Base!$M$2:$M$296,Base!$D$2:$D$296,">="&DATE(2024,4,1),Base!$D$2:$D$296,"<"&DATE(2024,5,1)) -> 610
G21: 5 | H21: =SUMIFS(Base!$M$2:$M$296,Base!$D$2:$D$296,">="&DATE(2024,5,1),Base!$D$2:$D$296,"<"&DATE(2024,6,1)) -> 720
G22: 6 | H22: =SUMIFS(Base!$M$2:$M$296,Base!$D$2:$D$296,">="&DATE(2024,6,1),Base!$D$2:$D$296,"<"&DATE(2024,7,1)) -> 710
G23: 7 | H23: =SUMIFS(Base!$M$2:$M$296,Base!$D$2:$D$296,">="&DATE(2024,7,1),Base!$D$2:$D$296,"<"&DATE(2024,8,1)) -> 746
G24: 8 | H24: =SUMIFS(Base!$M$2:$M$296,Base!$D$2:$D$296,">="&DATE(2024,8,1),Base!$D$2:$D$296,"<"&DATE(2024,9,1)) -> 660
G25: 9 | H25: =SUMIFS(Base!$M$2:$M$296,Base!$D$2:$D$296,">="&DATE(2024,9,1),Base!$D$2:$D$296,"<"&DATE(2024,10,1)) -> 587
G26: 10 | H26: =SUMIFS(Base!$M$2:$M$296,Base!$D$2:$D$296,">="&DATE(2024,10,1),Base!$D$2:$D$296,"<"&DATE(2024,11,1)) -> 620
G27: 11 | H27: =SUMIFS(Base!$M$2:$M$296,Base!$D$2:$D$296,">="&DATE(2024,11,1),Base!$D$2:$D$296,"<"&DATE(2024,12,1)) -> 520
G28: 12 | H28: =SUMIFS(Base!$M$2:$M$296,Base!$D$2:$D$296,">="&DATE(2024,12,1),Base!$D$2:$D$296,"<"&DATE(2025,1,1)) -> 330

Sheet Dashboard
A1: XBOX GAME PASS — SALES DASHBOARD
A4: Visão executiva de assinaturas, receita e add-ons • Base demonstrativa reconstruída • 2024
A5: ASSINANTES | D5: RECEITA TOTAL | G5: EA PLAY | J5: MINECRAFT | M5: AUTO RENEWAL YES R$ 3.786
A6: =Calculos!B4 -> 295 | D6: =Calculos!B5 -> 7633 | G6: =Calculos!B6 -> 2940 | J6: =Calculos!B7 -> 3880
M8: AUTO RENEWAL NO R$ 3.847
A12: RECEITA POR PLANO | H12: RECEITA POR PERIODICIDADE
A27: RENOVAÇÃO AUTOMÁTICA | H27: TENDÊNCIA MENSAL
A41: ="TICKET MÉDIO | R$ "&TEXT(Calculos!B5/Calculos!B4,"0.00") -> TICKET MÉDIO | R$ 026 | G41: 295 REGISTROS 01/01 a 16/12/2024 | K41: DASHBOARD EDUCACIONAL DIO • EXCEL

Sheet Leia-me
A1: README INTERNO — Dashboard Xbox Game Pass
A3: Objetivo | B3: Transformar uma base de assinaturas Xbox Game Pass em um dashboard executivo de vendas.
A4: Origem dos campos | B4: Estrutura baseada no desafio público da DIO e em documentação pública de projetos equivalentes.
A5: Importante | B5: O arquivo base original da DIO não pôde ser baixado pelo ambiente. A aba Base foi reconstruída de forma demonstrativa com 295 registros, preservando a estrutura dos 13 campos e os principais totais públicos conhecidos.
A6: Totais preservados | B6: 295 assinantes; Receita total R$ 7.633; EA Play R$ 2.940; Minecraft R$ 3.880; Auto Renewal Yes R$ 3.786; No R$ 3.847.
A7: Como substituir pela base oficial | B7: Cole os 295 registros oficiais na aba Base, mantendo os mesmos cabeçalhos. As fórmulas e gráficos continuarão usando as colunas da estrutura.
A8: Abas | B8: Dashboard = painel visual; Calculos = agregações; Base = registros; Leia-me = documentação.
A10: Fonte | B10: URL
A11: Desafio / material DIO | B11: https://hermes.dio.me/files/assets/805d54f9-6d53-4246-bed7-4aa2da615923.xlsx
A12: Documentação pública usada para estrutura/totais | B12: https://github.com/juliasenna13/xbox-game-pass-dashboard-excel
